wodpy/__init__.py
wodpy/extra.py
wodpy/wod.py
wodpy/wodfake.py
wodpy/wodnc.py
wodpy-2.0.0b1.dist-info/LICENSE
wodpy-2.0.0b1.dist-info/METADATA
wodpy-2.0.0b1.dist-info/WHEEL
wodpy-2.0.0b1.dist-info/top_level.txt
wodpy-2.0.0b1.dist-info/RECORD
