Metadata-Version: 2.1
Name: wodpy
Version: 2.0.0b1
Summary: A parser for World Ocean Data files, both ASCII described in http://data.nodc.noaa.gov/woa/WOD/DOC/wodreadme.pdf, and the equivalent netCDF.
Author: Simon Good, Bill Mills
License: The MIT License (MIT)
Project-URL: Homepage, https://github.com/IQuOD/wodpy
Classifier: License :: OSI Approved :: MIT License
Classifier: Programming Language :: Python
Classifier: Programming Language :: Python :: 3
Requires-Python: >=3.9
License-File: LICENSE
Requires-Dist: numpy
Requires-Dist: pandas
Requires-Dist: netCDF4
Provides-Extra: parallel
Requires-Dist: loky >=3.0 ; extra == 'parallel'
